[
    {
        "id": 2,
        "name": "Admin",
        "email": "admin@admin.com",
        "email_verified_at": "2025-09-01 13:38:54",
        "password": "$2y$10$K6JBy1OQIUo55jnpaoCMM.ds.RuxyBm7J5lKmlOUMUH1eFLzXuSym",
        "remember_token": "hO3X17sQ8rBUYoo1UYzz0lfrKuBN7LweUz3Avu08xXtkChJFLyDJSdxK1O0C",
        "created_at": "2025-09-01 13:38:54",
        "updated_at": "2025-09-07 00:36:10",
        "oauth_id": null,
        "oauth_type": null,
        "avatar": "uploads\/avatar\/padrao.webp",
        "last_name": null,
        "cpf": null,
        "phone": null,
        "logged_in": 0,
        "banned": 0,
        "inviter": null,
        "inviter_code": null,
        "affiliate_revenue_share": 0,
        "affiliate_revenue_share_fake": 0,
        "affiliate_cpa": "0.00",
        "affiliate_baseline": "0.00",
        "is_demo_agent": 0,
        "status": "active",
        "language": "pt_BR",
        "role_id": 3
    },
    {
        "id": 25,
        "name": "Teste User 5",
        "email": "teste5@lucrativabet.com",
        "email_verified_at": null,
        "password": "$2y$10$TxZnq6NfeGDAzEJtv7AUkumqe2WiRtlbdrBjS6A.J6DiyuSn0fFP.",
        "remember_token": null,
        "created_at": "2025-09-06 20:37:40",
        "updated_at": "2025-09-07 01:37:40",
        "oauth_id": null,
        "oauth_type": null,
        "avatar": "uploads\/avatar\/padrao.webp",
        "last_name": null,
        "cpf": null,
        "phone": null,
        "logged_in": 0,
        "banned": 0,
        "inviter": null,
        "inviter_code": null,
        "affiliate_revenue_share": 0,
        "affiliate_revenue_share_fake": 0,
        "affiliate_cpa": "0.00",
        "affiliate_baseline": "0.00",
        "is_demo_agent": 0,
        "status": "active",
        "language": "pt_BR",
        "role_id": 3
    },
    {
        "id": 24,
        "name": "Teste User 4",
        "email": "teste4@lucrativabet.com",
        "email_verified_at": null,
        "password": "$2y$10$ZTZ9OU4BOK5IpCm7ttVP7O2ApyAkOcWk8xUmBLFKYFr3Q1j91yd2C",
        "remember_token": null,
        "created_at": "2025-09-06 11:37:40",
        "updated_at": "2025-09-07 01:37:40",
        "oauth_id": null,
        "oauth_type": null,
        "avatar": "uploads\/avatar\/padrao.webp",
        "last_name": null,
        "cpf": null,
        "phone": null,
        "logged_in": 0,
        "banned": 0,
        "inviter": null,
        "inviter_code": null,
        "affiliate_revenue_share": 0,
        "affiliate_revenue_share_fake": 0,
        "affiliate_cpa": "0.00",
        "affiliate_baseline": "0.00",
        "is_demo_agent": 0,
        "status": "active",
        "language": "pt_BR",
        "role_id": 3
    },
    {
        "id": 23,
        "name": "Teste User 3",
        "email": "teste3@lucrativabet.com",
        "email_verified_at": null,
        "password": "$2y$10$VeDoI5COhX\/Jdk7quDhihuC5aG0NDYt\/gM8cjpX3cp8fu7xLD1Clu",
        "remember_token": null,
        "created_at": "2025-09-06 01:37:39",
        "updated_at": "2025-09-07 01:37:40",
        "oauth_id": null,
        "oauth_type": null,
        "avatar": "uploads\/avatar\/padrao.webp",
        "last_name": null,
        "cpf": null,
        "phone": null,
        "logged_in": 0,
        "banned": 0,
        "inviter": null,
        "inviter_code": null,
        "affiliate_revenue_share": 0,
        "affiliate_revenue_share_fake": 0,
        "affiliate_cpa": "0.00",
        "affiliate_baseline": "0.00",
        "is_demo_agent": 0,
        "status": "active",
        "language": "pt_BR",
        "role_id": 3
    },
    {
        "id": 21,
        "name": "Teste User 1",
        "email": "teste1@lucrativabet.com",
        "email_verified_at": null,
        "password": "$2y$10$d7DXFCi52q5IK4Hotir5.eQQL\/5bLrFZyeZbA32zUeDsnahR1XN6q",
        "remember_token": null,
        "created_at": "2025-09-07 00:37:39",
        "updated_at": "2025-09-07 01:37:39",
        "oauth_id": null,
        "oauth_type": null,
        "avatar": "uploads\/avatar\/padrao.webp",
        "last_name": null,
        "cpf": null,
        "phone": null,
        "logged_in": 0,
        "banned": 0,
        "inviter": null,
        "inviter_code": null,
        "affiliate_revenue_share": 0,
        "affiliate_revenue_share_fake": 0,
        "affiliate_cpa": "0.00",
        "affiliate_baseline": "0.00",
        "is_demo_agent": 0,
        "status": "active",
        "language": "pt_BR",
        "role_id": 3
    },
    {
        "id": 22,
        "name": "Teste User 2",
        "email": "teste2@lucrativabet.com",
        "email_verified_at": null,
        "password": "$2y$10$j\/MuOgIEyqgw0b70jUAiXOx3INInhZC\/TMmbDz0aqn2FyWvzw5CCu",
        "remember_token": null,
        "created_at": "2025-09-06 19:37:39",
        "updated_at": "2025-09-07 01:37:39",
        "oauth_id": null,
        "oauth_type": null,
        "avatar": "uploads\/avatar\/padrao.webp",
        "last_name": null,
        "cpf": null,
        "phone": null,
        "logged_in": 0,
        "banned": 0,
        "inviter": null,
        "inviter_code": null,
        "affiliate_revenue_share": 0,
        "affiliate_revenue_share_fake": 0,
        "affiliate_cpa": "0.00",
        "affiliate_baseline": "0.00",
        "is_demo_agent": 0,
        "status": "active",
        "language": "pt_BR",
        "role_id": 3
    },
    {
        "id": 15,
        "name": "Lucrativa Admin",
        "email": "lucrativa@bet.com",
        "email_verified_at": "2025-09-07 00:44:17",
        "password": "$2y$10$I5LkgodKIFS\/xpc80HyYde.GV30afg.6Na5BMjQDR0z5z7cPLeQHi",
        "remember_token": "j1CO8XtCJmlNxCOYNatbve0Jdul62MeoWW6oTxr8eSZtiDv2gdIpuifKKBSk",
        "created_at": "2025-09-07 00:36:10",
        "updated_at": "2025-09-07 00:36:10",
        "oauth_id": null,
        "oauth_type": null,
        "avatar": "uploads\/avatar\/padrao.webp",
        "last_name": null,
        "cpf": null,
        "phone": null,
        "logged_in": 0,
        "banned": 0,
        "inviter": null,
        "inviter_code": null,
        "affiliate_revenue_share": 0,
        "affiliate_revenue_share_fake": 0,
        "affiliate_cpa": "0.00",
        "affiliate_baseline": "0.00",
        "is_demo_agent": 0,
        "status": "active",
        "language": "pt_BR",
        "role_id": 3
    },
    {
        "id": 14,
        "name": "Dev Lucrativa",
        "email": "dev@lucrativabet.com",
        "email_verified_at": null,
        "password": "$2y$10$9s1D4bh9LB7yKxz1AXmUvurkDAzi0ATL\/H2IOXzDH\/wjfMR\/XOCvy",
        "remember_token": null,
        "created_at": "2025-09-06 23:38:05",
        "updated_at": "2025-09-07 00:36:10",
        "oauth_id": null,
        "oauth_type": null,
        "avatar": "uploads\/avatar\/padrao.webp",
        "last_name": null,
        "cpf": null,
        "phone": null,
        "logged_in": 0,
        "banned": 0,
        "inviter": null,
        "inviter_code": null,
        "affiliate_revenue_share": 0,
        "affiliate_revenue_share_fake": 0,
        "affiliate_cpa": "0.00",
        "affiliate_baseline": "0.00",
        "is_demo_agent": 0,
        "status": "active",
        "language": "pt_BR",
        "role_id": 3
    },
    {
        "id": 13,
        "name": "Admin Lucrativa",
        "email": "admin@lucrativabet.com",
        "email_verified_at": null,
        "password": "$2y$10$7xqKtUJMgtU9AHU6J5dZ9etp9\/ep4IHzrce7W0usw5L.43CMHo6wW",
        "remember_token": null,
        "created_at": "2025-09-06 23:38:05",
        "updated_at": "2025-09-07 00:36:10",
        "oauth_id": null,
        "oauth_type": null,
        "avatar": "uploads\/avatar\/padrao.webp",
        "last_name": null,
        "cpf": null,
        "phone": null,
        "logged_in": 0,
        "banned": 0,
        "inviter": null,
        "inviter_code": null,
        "affiliate_revenue_share": 0,
        "affiliate_revenue_share_fake": 0,
        "affiliate_cpa": "0.00",
        "affiliate_baseline": "0.00",
        "is_demo_agent": 0,
        "status": "active",
        "language": "pt_BR",
        "role_id": 3
    }
]